libbruteforce-0.1.0.dist-info/METADATA
libbruteforce-0.1.0.dist-info/WHEEL
libbruteforce-0.1.0.dist-info/licenses/LICENSE
libbruteforce-0.1.0.dist-info/licenses/LICENSE-MIT-libbruteforce
libbruteforce/__init__.py
libbruteforce/libbruteforce.cpython-38-aarch64-linux-gnu.so
libbruteforce-0.1.0.dist-info/RECORD
