Metadata-Version: 2.4
Name: libbruteforce
Version: 0.1.0
Classifier: Development Status :: 3 - Alpha
Classifier: License :: OSI Approved :: MIT License
Classifier: Programming Language :: Rust
Classifier: Programming Language :: Python :: Implementation :: CPython
Classifier: Programming Language :: Python :: Implementation :: PyPy
Classifier: Programming Language :: Python :: 3.8
Classifier: Programming Language :: Python :: 3.9
Classifier: Programming Language :: Python :: 3.10
Classifier: Programming Language :: Python :: 3.11
Classifier: Programming Language :: Python :: 3.12
Classifier: Programming Language :: Python :: 3.13
Classifier: Programming Language :: Python :: 3.13
Classifier: Topic :: Security
Classifier: Topic :: Security :: Cryptography
License-File: LICENSE
License-File: LICENSE-MIT-libbruteforce
Summary: Rust bindings for the libbruteforce Rust crate
Author-email: Jayson Fong <jayson.fong@gatech.edu>
License: MIT
Requires-Python: >=3.8
Project-URL: Homepage, https://github.com/Jayson-Fong/python-libbruteforce
Project-URL: Issues, https://github.com/Jayson-Fong/python-libbruteforce/issues
